nost/__init__.py
nost/__main__.py
nost/_version.py
nost/backend.py
nost/credentials.py
nost/logger.py
nost/plugins.py
nost/storages.py
nost/vaults.py
nost/utils/__init__.py
nost/utils/encryption.py
nost/utils/localvaults.py
nostplugins/__init__.py
nostplugins/git.py
nostplugins/gitlab_api.py
nostplugins/rsync.py
nostplugins/ssh.py
nostplugins/webdav.py
nosaastrust-1.0.dist-info/METADATA
nosaastrust-1.0.dist-info/WHEEL
nosaastrust-1.0.dist-info/entry_points.txt
nosaastrust-1.0.dist-info/RECORD
