Metadata-Version: 2.3
Name: nosaastrust
Version: 1.0
Summary: Backup manager to fetch suppliers backups and store
Project-URL: Homepage, https://gitlab.com/syslinbit/drafts/noSaasTrust
Author-email: Syslinbit <contact@syslinbit.com>
License-Expression: BSD-2-Clause-Patent
Classifier: Intended Audience :: Information Technology
Classifier: License :: OSI Approved :: BSD License
Classifier: Operating System :: OS Independent
Classifier: Programming Language :: Python :: 3
Requires-Python: >=3.11
Requires-Dist: cryptography
Requires-Dist: pyyaml
Requires-Dist: requests
Provides-Extra: docs
Requires-Dist: myst-parser>=2.0.0; extra == 'docs'
Requires-Dist: sphinx-rtd-theme>=2.0.0; extra == 'docs'
Requires-Dist: sphinx>=7.2.6; extra == 'docs'
Provides-Extra: extra
Requires-Dist: pre-commit>=3.6.0; extra == 'extra'
Provides-Extra: lint
Requires-Dist: flake8-simplify; extra == 'lint'
Requires-Dist: flake8>=3.5.0; extra == 'lint'
Provides-Extra: publish
Requires-Dist: keyring; extra == 'publish'
Requires-Dist: keyrings-alt; extra == 'publish'
Provides-Extra: test
Requires-Dist: pytest>=4.6; extra == 'test'
